[{"id": 30835, "identifier": "quran-kids", "surah_number": 87, "surah_ar_name": "\u0633\u0648\u0631\u0629 \u0627\u0644\u0623\u0639\u0644\u0649", "surah_en_name": "Al-A'laa", "surah_en_name_translation": "The Most High", "revelation_type": "Meccan", "juz": 30, "manzil": 7, "page": 591, "ruku": 529, "hizb_quarter": 237, "sajda": false, "sajda_id": 0, "sajda_obligatory": false, "sajda_recommended": false, "language": "ar", "name": "Kids", "transelator_en_name": "Kids", "format": "text", "type": "quran", "ayah_number": 5949, "text": "\u0633\u064e\u0628\u0651\u0650\u062d\u0650|Glorify|62|111|18042$\u0671\u0633\u0652\u0645\u064e|(the) name|94|192|4761$\u0631\u064e\u0628\u0651\u0650\u0643\u064e|(of) your Lord,|117|215|1322$\u0671\u0644\u0652\u0623\u064e\u0639\u0652\u0644\u064e\u0649|the Most High,|117|166|10009$"}, {"id": 30836, "identifier": "quran-kids", "surah_number": 87, "surah_ar_name": "\u0633\u0648\u0631\u0629 \u0627\u0644\u0623\u0639\u0644\u0649", "surah_en_name": "Al-A'laa", "surah_en_name_translation": "The Most High", "revelation_type": "Meccan", "juz": 30, "manzil": 7, "page": 591, "ruku": 529, "hizb_quarter": 237, "sajda": false, "sajda_id": 0, "sajda_obligatory": false, "sajda_recommended": false, "language": "ar", "name": "Kids", "transelator_en_name": "Kids", "format": "text", "type": "quran", "ayah_number": 5950, "text": "\u0671\u0644\u0651\u064e\u0630\u0650\u0649|The One Who|110|199|138$\u062e\u064e\u0644\u064e\u0642\u064e|created,|76|254|299$\u0641\u064e\u0633\u064e\u0648\u0651\u064e\u0649\u0670|then proportioned,|143|232|17630$"}, {"id": 30837, "identifier": "quran-kids", "surah_number": 87, "surah_ar_name": "\u0633\u0648\u0631\u0629 \u0627\u0644\u0623\u0639\u0644\u0649", "surah_en_name": "Al-A'laa", "surah_en_name_translation": "The Most High", "revelation_type": "Meccan", "juz": 30, "manzil": 7, "page": 591, "ruku": 529, "hizb_quarter": 237, "sajda": false, "sajda_id": 0, "sajda_obligatory": false, "sajda_recommended": false, "language": "ar", "name": "Kids", "transelator_en_name": "Kids", "format": "text", "type": "quran", "ayah_number": 5951, "text": "\u0648\u064e\u0671\u0644\u0651\u064e\u0630\u0650\u0649|And the One Who|137|228|6481$\u0642\u064e\u062f\u0651\u064e\u0631\u064e|measured|83|264|17538$\u0641\u064e\u0647\u064e\u062f\u064e\u0649\u0670|then guided,|103|194|18043$"}, {"id": 30838, "identifier": "quran-kids", "surah_number": 87, "surah_ar_name": "\u0633\u0648\u0631\u0629 \u0627\u0644\u0623\u0639\u0644\u0649", "surah_en_name": "Al-A'laa", "surah_en_name_translation": "The Most High", "revelation_type": "Meccan", "juz": 30, "manzil": 7, "page": 591, "ruku": 529, "hizb_quarter": 237, "sajda": false, "sajda_id": 0, "sajda_obligatory": false, "sajda_recommended": false, "language": "ar", "name": "Kids", "transelator_en_name": "Kids", "format": "text", "type": "quran", "ayah_number": 5952, "text": "\u0648\u064e\u0671\u0644\u0651\u064e\u0630\u0650\u0649\u0653|And the One Who|137|224|6481$\u0623\u064e\u062e\u0652\u0631\u064e\u062c\u064e|brings forth|96|271|6338$\u0671\u0644\u0652\u0645\u064e\u0631\u0652\u0639\u064e\u0649\u0670|the pasture,|102|190|18044$"}, {"id": 30839, "identifier": "quran-kids", "surah_number": 87, "surah_ar_name": "\u0633\u0648\u0631\u0629 \u0627\u0644\u0623\u0639\u0644\u0649", "surah_en_name": "Al-A'laa", "surah_en_name_translation": "The Most High", "revelation_type": "Meccan", "juz": 30, "manzil": 7, "page": 591, "ruku": 529, "hizb_quarter": 237, "sajda": false, "sajda_id": 0, "sajda_obligatory": false, "sajda_recommended": false, "language": "ar", "name": "Kids", "transelator_en_name": "Kids", "format": "text", "type": "quran", "ayah_number": 5953, "text": "\u0641\u064e\u062c\u064e\u0639\u064e\u0644\u064e\u0647\u064f\u06e5|And then made it|134|234|12814$\u063a\u064f\u062b\u064e\u0627\u0653\u0621\u064b|stubble,|73|273|12289$\u0623\u064e\u062d\u0652\u0648\u064e\u0649\u0670|dark.|78|178|18045$"}, {"id": 30840, "identifier": "quran-kids", "surah_number": 87, "surah_ar_name": "\u0633\u0648\u0631\u0629 \u0627\u0644\u0623\u0639\u0644\u0649", "surah_en_name": "Al-A'laa", "surah_en_name_translation": "The Most High", "revelation_type": "Meccan", "juz": 30, "manzil": 7, "page": 591, "ruku": 529, "hizb_quarter": 237, "sajda": false, "sajda_id": 0, "sajda_obligatory": false, "sajda_recommended": false, "language": "ar", "name": "Kids", "transelator_en_name": "Kids", "format": "text", "type": "quran", "ayah_number": 5954, "text": "\u0633\u064e\u0646\u064f\u0642\u0652\u0631\u0650\u0626\u064f\u0643\u064e|We will make you recite|177|259|18046$\u0641\u064e\u0644\u064e\u0627|so not|62|226|208$\u062a\u064e\u0646\u0633\u064e\u0649\u0670\u0653|you will forget,|119|201|18047$"}, {"id": 30841, "identifier": "quran-kids", "surah_number": 87, "surah_ar_name": "\u0633\u0648\u0631\u0629 \u0627\u0644\u0623\u0639\u0644\u0649", "surah_en_name": "Al-A'laa", "surah_en_name_translation": "The Most High", "revelation_type": "Meccan", "juz": 30, "manzil": 7, "page": 591, "ruku": 529, "hizb_quarter": 237, "sajda": false, "sajda_id": 0, "sajda_obligatory": false, "sajda_recommended": false, "language": "ar", "name": "Kids", "transelator_en_name": "Kids", "format": "text", "type": "quran", "ayah_number": 5955, "text": "\u0625\u0650\u0644\u0651\u064e\u0627|Except|65|79|86$\u0645\u064e\u0627|what|53|81|262$\u0634\u064e\u0627\u0653\u0621\u064e \u0671\u0644\u0644\u0651\u064e\u0647\u064f\u200c\u06da|Allah wills|99|127|180$\u0625\u0650\u0646\u0651\u064e\u0647\u064f\u06e5|Indeed, He|92|120|396$\u064a\u064e\u0639\u0652\u0644\u064e\u0645\u064f|knows|61|89|742$\u0671\u0644\u0652\u062c\u064e\u0647\u0652\u0631\u064e|the manifest|103|131|11952$\u0648\u064e\u0645\u064e\u0627|and what|82|96|46$\u064a\u064e\u062e\u0652\u0641\u064e\u0649\u0670|is hidden.|83|83|2615$"}, {"id": 30842, "identifier": "quran-kids", "surah_number": 87, "surah_ar_name": "\u0633\u0648\u0631\u0629 \u0627\u0644\u0623\u0639\u0644\u0649", "surah_en_name": "Al-A'laa", "surah_en_name_translation": "The Most High", "revelation_type": "Meccan", "juz": 30, "manzil": 7, "page": 591, "ruku": 529, "hizb_quarter": 237, "sajda": false, "sajda_id": 0, "sajda_obligatory": false, "sajda_recommended": false, "language": "ar", "name": "Kids", "transelator_en_name": "Kids", "format": "text", "type": "quran", "ayah_number": 5956, "text": "\u0648\u064e\u0646\u064f\u064a\u064e\u0633\u0651\u0650\u0631\u064f\u0643\u064e|And We will ease you|161|372|18048$\u0644\u0650\u0644\u0652\u064a\u064f\u0633\u0652\u0631\u064e\u0649\u0670|to the ease.|102|313|18049$"}, {"id": 30843, "identifier": "quran-kids", "surah_number": 87, "surah_ar_name": "\u0633\u0648\u0631\u0629 \u0627\u0644\u0623\u0639\u0644\u0649", "surah_en_name": "Al-A'laa", "surah_en_name_translation": "The Most High", "revelation_type": "Meccan", "juz": 30, "manzil": 7, "page": 591, "ruku": 529, "hizb_quarter": 237, "sajda": false, "sajda_id": 0, "sajda_obligatory": false, "sajda_recommended": false, "language": "ar", "name": "Kids", "transelator_en_name": "Kids", "format": "text", "type": "quran", "ayah_number": 5957, "text": "\u0641\u064e\u0630\u064e\u0643\u0651\u0650\u0631\u0652|So remind,|90|152|16103$\u0625\u0650\u0646|if|44|167|225$\u0646\u0651\u064e\u0641\u064e\u0639\u064e\u062a\u0650|benefits|73|196|18050$\u0671\u0644\u0630\u0651\u0650\u0643\u0652\u0631\u064e\u0649\u0670|the reminder.|108|170|5700$"}, {"id": 30844, "identifier": "quran-kids", "surah_number": 87, "surah_ar_name": "\u0633\u0648\u0631\u0629 \u0627\u0644\u0623\u0639\u0644\u0649", "surah_en_name": "Al-A'laa", "surah_en_name_translation": "The Most High", "revelation_type": "Meccan", "juz": 30, "manzil": 7, "page": 591, "ruku": 529, "hizb_quarter": 237, "sajda": false, "sajda_id": 0, "sajda_obligatory": false, "sajda_recommended": false, "language": "ar", "name": "Kids", "transelator_en_name": "Kids", "format": "text", "type": "quran", "ayah_number": 5958, "text": "\u0633\u064e\u064a\u064e\u0630\u0651\u064e\u0643\u0651\u064e\u0631\u064f|He will pay heed -|140|225|18051$\u0645\u064e\u0646|(one) who|88|258|76$\u064a\u064e\u062e\u0652\u0634\u064e\u0649\u0670|fears (Allah).|106|191|11338$"}, {"id": 30845, "identifier": "quran-kids", "surah_number": 87, "surah_ar_name": "\u0633\u0648\u0631\u0629 \u0627\u0644\u0623\u0639\u0644\u0649", "surah_en_name": "Al-A'laa", "surah_en_name_translation": "The Most High", "revelation_type": "Meccan", "juz": 30, "manzil": 7, "page": 591, "ruku": 529, "hizb_quarter": 237, "sajda": false, "sajda_id": 0, "sajda_obligatory": false, "sajda_recommended": false, "language": "ar", "name": "Kids", "transelator_en_name": "Kids", "format": "text", "type": "quran", "ayah_number": 5959, "text": "\u0648\u064e\u064a\u064e\u062a\u064e\u062c\u064e\u0646\u0651\u064e\u0628\u064f\u0647\u064e\u0627|And will avoid it|124|328|18052$\u0671\u0644\u0652\u0623\u064e\u0634\u0652\u0642\u064e\u0649|the wretched one.|143|347|18053$"}, {"id": 30846, "identifier": "quran-kids", "surah_number": 87, "surah_ar_name": "\u0633\u0648\u0631\u0629 \u0627\u0644\u0623\u0639\u0644\u0649", "surah_en_name": "Al-A'laa", "surah_en_name_translation": "The Most High", "revelation_type": "Meccan", "juz": 30, "manzil": 7, "page": 591, "ruku": 529, "hizb_quarter": 237, "sajda": false, "sajda_id": 0, "sajda_obligatory": false, "sajda_recommended": false, "language": "ar", "name": "Kids", "transelator_en_name": "Kids", "format": "text", "type": "quran", "ayah_number": 5960, "text": "\u0671\u0644\u0651\u064e\u0630\u0650\u0649|The one who|106|154|138$\u064a\u064e\u0635\u0652\u0644\u064e\u0649|will burn|81|178|18054$\u0671\u0644\u0646\u0651\u064e\u0627\u0631\u064e|(in) the Fire|99|196|231$\u0671\u0644\u0652\u0643\u064f\u0628\u0652\u0631\u064e\u0649\u0670|[the] great.|99|147|11391$"}, {"id": 30847, "identifier": "quran-kids", "surah_number": 87, "surah_ar_name": "\u0633\u0648\u0631\u0629 \u0627\u0644\u0623\u0639\u0644\u0649", "surah_en_name": "Al-A'laa", "surah_en_name_translation": "The Most High", "revelation_type": "Meccan", "juz": 30, "manzil": 7, "page": 591, "ruku": 529, "hizb_quarter": 237, "sajda": false, "sajda_id": 0, "sajda_obligatory": false, "sajda_recommended": false, "language": "ar", "name": "Kids", "transelator_en_name": "Kids", "format": "text", "type": "quran", "ayah_number": 5961, "text": "\u062b\u064f\u0645\u0651\u064e|Then|53|82|293$\u0644\u064e\u0627|not|42|99|30$\u064a\u064e\u0645\u064f\u0648\u062a\u064f|he will die|85|142|9961$\u0641\u0650\u064a\u0647\u064e\u0627|therein|66|123|253$\u0648\u064e\u0644\u064e\u0627|and not|71|128|25$\u064a\u064e\u062d\u0652\u064a\u064e\u0649\u0670|will live.|72|101|11091$"}, {"id": 30848, "identifier": "quran-kids", "surah_number": 87, "surah_ar_name": "\u0633\u0648\u0631\u0629 \u0627\u0644\u0623\u0639\u0644\u0649", "surah_en_name": "Al-A'laa", "surah_en_name_translation": "The Most High", "revelation_type": "Meccan", "juz": 30, "manzil": 7, "page": 591, "ruku": 529, "hizb_quarter": 237, "sajda": false, "sajda_id": 0, "sajda_obligatory": false, "sajda_recommended": false, "language": "ar", "name": "Kids", "transelator_en_name": "Kids", "format": "text", "type": "quran", "ayah_number": 5962, "text": "\u0642\u064e\u062f\u0652|Certainly,|83|125|1097$\u0623\u064e\u0641\u0652\u0644\u064e\u062d\u064e|has succeeded|119|203|11500$\u0645\u064e\u0646|(one) who|88|172|76$\u062a\u064e\u0632\u064e\u0643\u0651\u064e\u0649\u0670|purifies (himself),|134|176|11534$"}, {"id": 30803, "identifier": "quran-kids", "surah_number": 87, "surah_ar_name": "\u0633\u0648\u0631\u0629 \u0627\u0644\u0623\u0639\u0644\u0649", "surah_en_name": "Al-A'laa", "surah_en_name_translation": "The Most High", "revelation_type": "Meccan", "juz": 30, "manzil": 7, "page": 591, "ruku": 529, "hizb_quarter": 237, "sajda": false, "sajda_id": 0, "sajda_obligatory": false, "sajda_recommended": false, "language": "ar", "name": "Kids", "transelator_en_name": "Kids", "format": "text", "type": "quran", "ayah_number": 5963, "text": "\u0648\u064e\u0630\u064e\u0643\u064e\u0631\u064e|And remembers|121|166|13979$\u0671\u0633\u0652\u0645\u064e|(the) name|94|184|4761$\u0631\u064e\u0628\u0651\u0650\u0647\u0650\u06e6|(of) his Lord|101|191|392$\u0641\u064e\u0635\u064e\u0644\u0651\u064e\u0649\u0670|and prays.|90|135|18055$"}, {"id": 30850, "identifier": "quran-kids", "surah_number": 87, "surah_ar_name": "\u0633\u0648\u0631\u0629 \u0627\u0644\u0623\u0639\u0644\u0649", "surah_en_name": "Al-A'laa", "surah_en_name_translation": "The Most High", "revelation_type": "Meccan", "juz": 30, "manzil": 7, "page": 592, "ruku": 529, "hizb_quarter": 237, "sajda": false, "sajda_id": 0, "sajda_obligatory": false, "sajda_recommended": false, "language": "ar", "name": "Kids", "transelator_en_name": "Kids", "format": "text", "type": "quran", "ayah_number": 5964, "text": "\u0628\u064e\u0644\u0652|Nay!|50|105|848$\u062a\u064f\u0624\u0652\u062b\u0650\u0631\u064f\u0648\u0646\u064e|You prefer|97|207|18056$\u0671\u0644\u0652\u062d\u064e\u064a\u064e\u0648\u0672\u0629\u064e|the life|82|192|823$\u0671\u0644\u062f\u0651\u064f\u0646\u0652\u064a\u064e\u0627|(of) the world,|117|172|818$"}, {"id": 30851, "identifier": "quran-kids", "surah_number": 87, "surah_ar_name": "\u0633\u0648\u0631\u0629 \u0627\u0644\u0623\u0639\u0644\u0649", "surah_en_name": "Al-A'laa", "surah_en_name_translation": "The Most High", "revelation_type": "Meccan", "juz": 30, "manzil": 7, "page": 592, "ruku": 529, "hizb_quarter": 237, "sajda": false, "sajda_id": 0, "sajda_obligatory": false, "sajda_recommended": false, "language": "ar", "name": "Kids", "transelator_en_name": "Kids", "format": "text", "type": "quran", "ayah_number": 5965, "text": "\u0648\u064e\u0671\u0644\u0652\u0623\u064e\u062e\u0650\u0631\u064e\u0629\u064f|While the Hereafter|149|226|4213$\u062e\u064e\u064a\u0652\u0631\u064c|(is) better|88|242|520$\u0648\u064e\u0623\u064e\u0628\u0652\u0642\u064e\u0649\u0670\u0653|and ever lasting.|131|208|11521$"}, {"id": 30852, "identifier": "quran-kids", "surah_number": 87, "surah_ar_name": "\u0633\u0648\u0631\u0629 \u0627\u0644\u0623\u0639\u0644\u0649", "surah_en_name": "Al-A'laa", "surah_en_name_translation": "The Most High", "revelation_type": "Meccan", "juz": 30, "manzil": 7, "page": 592, "ruku": 529, "hizb_quarter": 237, "sajda": false, "sajda_id": 0, "sajda_obligatory": false, "sajda_recommended": false, "language": "ar", "name": "Kids", "transelator_en_name": "Kids", "format": "text", "type": "quran", "ayah_number": 5966, "text": "\u0625\u0650\u0646\u0651\u064e|Indeed,|70|98|58$\u0647\u064e\u0640\u0670\u0630\u064e\u0627|this|59|115|248$\u0644\u064e\u0641\u0650\u0649|surely (is) in|102|158|1513$\u0671\u0644\u0635\u0651\u064f\u062d\u064f\u0641\u0650|the Scriptures|114|170|11702$\u0671\u0644\u0652\u0623\u064f\u0648\u0644\u064e\u0649\u0670|[the] former,|106|134|11384$"}, {"id": 30853, "identifier": "quran-kids", "surah_number": 87, "surah_ar_name": "\u0633\u0648\u0631\u0629 \u0627\u0644\u0623\u0639\u0644\u0649", "surah_en_name": "Al-A'laa", "surah_en_name_translation": "The Most High", "revelation_type": "Meccan", "juz": 30, "manzil": 7, "page": 592, "ruku": 529, "hizb_quarter": 237, "sajda": false, "sajda_id": 0, "sajda_obligatory": false, "sajda_recommended": false, "language": "ar", "name": "Kids", "transelator_en_name": "Kids", "format": "text", "type": "quran", "ayah_number": 5967, "text": "\u0635\u064f\u062d\u064f\u0641\u0650|(The) Scriptures|129|217|16290$\u0625\u0650\u0628\u0652\u0631\u064e\u0672\u0647\u0650\u064a\u0645\u064e|(of) Ibrahim|98|274|1127$\u0648\u064e\u0645\u064f\u0648\u0633\u064e\u0649\u0670|and Musa.|97|185|5792$"}]