[{"id": 221634, "identifier": "en.asad", "surah_number": 33, "surah_ar_name": "\u0633\u0648\u0631\u0629 \u0627\u0644\u0623\u062d\u0632\u0627\u0628", "surah_en_name": "Al-Ahzaab", "surah_en_name_translation": "The Clans", "revelation_type": "Medinan", "juz": 21, "manzil": 5, "page": 418, "ruku": 361, "hizb_quarter": 167, "sajda": false, "sajda_id": 0, "sajda_obligatory": false, "sajda_recommended": false, "language": "en", "name": "Asad", "transelator_en_name": "Muhammad Asad", "format": "text", "type": "translation", "ayah_number": 3534, "text": "PROPHET! Remain conscious of God, and defer not to the deniers of the truth and the hypo\u00adcrites: for God is truly all-knowing, wise."}, {"id": 221635, "identifier": "en.asad", "surah_number": 33, "surah_ar_name": "\u0633\u0648\u0631\u0629 \u0627\u0644\u0623\u062d\u0632\u0627\u0628", "surah_en_name": "Al-Ahzaab", "surah_en_name_translation": "The Clans", "revelation_type": "Medinan", "juz": 21, "manzil": 5, "page": 418, "ruku": 361, "hizb_quarter": 167, "sajda": false, "sajda_id": 0, "sajda_obligatory": false, "sajda_recommended": false, "language": "en", "name": "Asad", "transelator_en_name": "Muhammad Asad", "format": "text", "type": "translation", "ayah_number": 3535, "text": "And follow [but] that which comes unto thee through revelation from thy Sustainer: for God is truly aware of all that you do, [O men]."}, {"id": 221636, "identifier": "en.asad", "surah_number": 33, "surah_ar_name": "\u0633\u0648\u0631\u0629 \u0627\u0644\u0623\u062d\u0632\u0627\u0628", "surah_en_name": "Al-Ahzaab", "surah_en_name_translation": "The Clans", "revelation_type": "Medinan", "juz": 21, "manzil": 5, "page": 418, "ruku": 361, "hizb_quarter": 167, "sajda": false, "sajda_id": 0, "sajda_obligatory": false, "sajda_recommended": false, "language": "en", "name": "Asad", "transelator_en_name": "Muhammad Asad", "format": "text", "type": "translation", "ayah_number": 3536, "text": "And place thy trust in God [alone]: for none is as worthy of trust as God."}, {"id": 221638, "identifier": "en.asad", "surah_number": 33, "surah_ar_name": "\u0633\u0648\u0631\u0629 \u0627\u0644\u0623\u062d\u0632\u0627\u0628", "surah_en_name": "Al-Ahzaab", "surah_en_name_translation": "The Clans", "revelation_type": "Medinan", "juz": 21, "manzil": 5, "page": 418, "ruku": 361, "hizb_quarter": 167, "sajda": false, "sajda_id": 0, "sajda_obligatory": false, "sajda_recommended": false, "language": "en", "name": "Asad", "transelator_en_name": "Muhammad Asad", "format": "text", "type": "translation", "ayah_number": 3537, "text": "NEVER has God endowed any man with two hearts in one body: and [just as] He has never made your wives whom you may have declared to be \u201cas unlawful to you as your mothers\u2019 bodies\u201d [truly] your mothers, so, too, has He never made your adopted sons [truly] your sons: these are but [figures of] speech uttered by your mouths - whereas God speaks the [absolute] truth: and it is He alone who can show [you] the right path."}, {"id": 221639, "identifier": "en.asad", "surah_number": 33, "surah_ar_name": "\u0633\u0648\u0631\u0629 \u0627\u0644\u0623\u062d\u0632\u0627\u0628", "surah_en_name": "Al-Ahzaab", "surah_en_name_translation": "The Clans", "revelation_type": "Medinan", "juz": 21, "manzil": 5, "page": 418, "ruku": 361, "hizb_quarter": 167, "sajda": false, "sajda_id": 0, "sajda_obligatory": false, "sajda_recommended": false, "language": "en", "name": "Asad", "transelator_en_name": "Muhammad Asad", "format": "text", "type": "translation", "ayah_number": 3538, "text": "[As for your adopted children,] call them by their [real] fathers\u2019 names: this is more equitable in the sight of God; and if you know not who their fathers were, [call them] your brethren in faith and your friends. However, you will incur no sin if you err in this respect: [what really matters is] but what your hearts intend - for God is indeed much-forgiv\u00ading, a dispenser of grace!"}, {"id": 221640, "identifier": "en.asad", "surah_number": 33, "surah_ar_name": "\u0633\u0648\u0631\u0629 \u0627\u0644\u0623\u062d\u0632\u0627\u0628", "surah_en_name": "Al-Ahzaab", "surah_en_name_translation": "The Clans", "revelation_type": "Medinan", "juz": 21, "manzil": 5, "page": 418, "ruku": 361, "hizb_quarter": 167, "sajda": false, "sajda_id": 0, "sajda_obligatory": false, "sajda_recommended": false, "language": "en", "name": "Asad", "transelator_en_name": "Muhammad Asad", "format": "text", "type": "translation", "ayah_number": 3539, "text": "The Prophet has a higher claim on the believers than [they have on] their own selves, [seeing that he is as a father to them] and his wives are their mothers: and they who are [thus] closely related have, in accordance with God\u2019s decree, a higher claim upon one another than [was even the case between] the believers [of Yathrib] and those who had migrated [there for the sake of God]. None the less, you are to act with utmost goodness towards your [other] close friends as well: this [too] is written down in God\u2019s decree."}, {"id": 221641, "identifier": "en.asad", "surah_number": 33, "surah_ar_name": "\u0633\u0648\u0631\u0629 \u0627\u0644\u0623\u062d\u0632\u0627\u0628", "surah_en_name": "Al-Ahzaab", "surah_en_name_translation": "The Clans", "revelation_type": "Medinan", "juz": 21, "manzil": 5, "page": 419, "ruku": 361, "hizb_quarter": 167, "sajda": false, "sajda_id": 0, "sajda_obligatory": false, "sajda_recommended": false, "language": "en", "name": "Asad", "transelator_en_name": "Muhammad Asad", "format": "text", "type": "translation", "ayah_number": 3540, "text": "AND LO! We did accept a solemn pledge from all the prophets from thee, [O Muhammad,] as well as from Noah, and Abraham, and Moses, and Jesus the son of Mary -: for We accepted a most weighty, solemn pledge from [all of] them,"}, {"id": 221642, "identifier": "en.asad", "surah_number": 33, "surah_ar_name": "\u0633\u0648\u0631\u0629 \u0627\u0644\u0623\u062d\u0632\u0627\u0628", "surah_en_name": "Al-Ahzaab", "surah_en_name_translation": "The Clans", "revelation_type": "Medinan", "juz": 21, "manzil": 5, "page": 419, "ruku": 361, "hizb_quarter": 167, "sajda": false, "sajda_id": 0, "sajda_obligatory": false, "sajda_recommended": false, "language": "en", "name": "Asad", "transelator_en_name": "Muhammad Asad", "format": "text", "type": "translation", "ayah_number": 3541, "text": "so that [at the end of time] He might ask those men of truth as to [what response] their truthfulness [had received on earth]. And grievous suffering has He readied for all who deny the truth!"}, {"id": 221643, "identifier": "en.asad", "surah_number": 33, "surah_ar_name": "\u0633\u0648\u0631\u0629 \u0627\u0644\u0623\u062d\u0632\u0627\u0628", "surah_en_name": "Al-Ahzaab", "surah_en_name_translation": "The Clans", "revelation_type": "Medinan", "juz": 21, "manzil": 5, "page": 419, "ruku": 362, "hizb_quarter": 167, "sajda": false, "sajda_id": 0, "sajda_obligatory": false, "sajda_recommended": false, "language": "en", "name": "Asad", "transelator_en_name": "Muhammad Asad", "format": "text", "type": "translation", "ayah_number": 3542, "text": "O YOU who have attained to faith! Call to mind the blessings which God bestowed on you (at the time) when [enemy] hosts came down upon you, where\u00adupon We let loose against them a storm wind and [heavenly] hosts that you could not see: yet God saw all that you did."}, {"id": 221644, "identifier": "en.asad", "surah_number": 33, "surah_ar_name": "\u0633\u0648\u0631\u0629 \u0627\u0644\u0623\u062d\u0632\u0627\u0628", "surah_en_name": "Al-Ahzaab", "surah_en_name_translation": "The Clans", "revelation_type": "Medinan", "juz": 21, "manzil": 5, "page": 419, "ruku": 362, "hizb_quarter": 167, "sajda": false, "sajda_id": 0, "sajda_obligatory": false, "sajda_recommended": false, "language": "en", "name": "Asad", "transelator_en_name": "Muhammad Asad", "format": "text", "type": "translation", "ayah_number": 3543, "text": "[Remember what you felt] when they came upon you from above you and from below you, and when [your] eyes became dim and [your] hearts came up to [your] throats, and [when] most conflicting thoughts about God passed through your minds:"}, {"id": 221645, "identifier": "en.asad", "surah_number": 33, "surah_ar_name": "\u0633\u0648\u0631\u0629 \u0627\u0644\u0623\u062d\u0632\u0627\u0628", "surah_en_name": "Al-Ahzaab", "surah_en_name_translation": "The Clans", "revelation_type": "Medinan", "juz": 21, "manzil": 5, "page": 419, "ruku": 362, "hizb_quarter": 167, "sajda": false, "sajda_id": 0, "sajda_obligatory": false, "sajda_recommended": false, "language": "en", "name": "Asad", "transelator_en_name": "Muhammad Asad", "format": "text", "type": "translation", "ayah_number": 3544, "text": "[for] there and then were the believers tried, and shaken with a shock severe."}, {"id": 221646, "identifier": "en.asad", "surah_number": 33, "surah_ar_name": "\u0633\u0648\u0631\u0629 \u0627\u0644\u0623\u062d\u0632\u0627\u0628", "surah_en_name": "Al-Ahzaab", "surah_en_name_translation": "The Clans", "revelation_type": "Medinan", "juz": 21, "manzil": 5, "page": 419, "ruku": 362, "hizb_quarter": 167, "sajda": false, "sajda_id": 0, "sajda_obligatory": false, "sajda_recommended": false, "language": "en", "name": "Asad", "transelator_en_name": "Muhammad Asad", "format": "text", "type": "translation", "ayah_number": 3545, "text": "And [remember how it was] when the hypo\u00adcrites and those with hearts diseased said [to one another], \u201cGod and His Apostle have promised us nothing but delusions!\u201d"}, {"id": 221647, "identifier": "en.asad", "surah_number": 33, "surah_ar_name": "\u0633\u0648\u0631\u0629 \u0627\u0644\u0623\u062d\u0632\u0627\u0628", "surah_en_name": "Al-Ahzaab", "surah_en_name_translation": "The Clans", "revelation_type": "Medinan", "juz": 21, "manzil": 5, "page": 419, "ruku": 362, "hizb_quarter": 167, "sajda": false, "sajda_id": 0, "sajda_obligatory": false, "sajda_recommended": false, "language": "en", "name": "Asad", "transelator_en_name": "Muhammad Asad", "format": "text", "type": "translation", "ayah_number": 3546, "text": "and when some of them said, \u201cO you people of Yathrib! You cannot withstand [the enemy] here: hence, go back [to your homes]!\u201d \u2014 Whereupon a party from among them asked leave of the Prophet, saying, \u201cBehold, our houses are exposed [to attack]!\u201d \u2014 The while they were not [really] exposed: they wanted nothing but to flee."}, {"id": 221648, "identifier": "en.asad", "surah_number": 33, "surah_ar_name": "\u0633\u0648\u0631\u0629 \u0627\u0644\u0623\u062d\u0632\u0627\u0628", "surah_en_name": "Al-Ahzaab", "surah_en_name_translation": "The Clans", "revelation_type": "Medinan", "juz": 21, "manzil": 5, "page": 419, "ruku": 362, "hizb_quarter": 167, "sajda": false, "sajda_id": 0, "sajda_obligatory": false, "sajda_recommended": false, "language": "en", "name": "Asad", "transelator_en_name": "Muhammad Asad", "format": "text", "type": "translation", "ayah_number": 3547, "text": "Now if their town had been stormed, and they had been asked [by the enemy] to commit apos\u00adtasy, [the hypocrites] would have done so without much delay"}, {"id": 221649, "identifier": "en.asad", "surah_number": 33, "surah_ar_name": "\u0633\u0648\u0631\u0629 \u0627\u0644\u0623\u062d\u0632\u0627\u0628", "surah_en_name": "Al-Ahzaab", "surah_en_name_translation": "The Clans", "revelation_type": "Medinan", "juz": 21, "manzil": 5, "page": 419, "ruku": 362, "hizb_quarter": 167, "sajda": false, "sajda_id": 0, "sajda_obligatory": false, "sajda_recommended": false, "language": "en", "name": "Asad", "transelator_en_name": "Muhammad Asad", "format": "text", "type": "translation", "ayah_number": 3548, "text": "although ere that they had vowed before God that they would never turn their backs [on His message]: and a vow made to God must surely be answered for!"}, {"id": 221650, "identifier": "en.asad", "surah_number": 33, "surah_ar_name": "\u0633\u0648\u0631\u0629 \u0627\u0644\u0623\u062d\u0632\u0627\u0628", "surah_en_name": "Al-Ahzaab", "surah_en_name_translation": "The Clans", "revelation_type": "Medinan", "juz": 21, "manzil": 5, "page": 420, "ruku": 362, "hizb_quarter": 167, "sajda": false, "sajda_id": 0, "sajda_obligatory": false, "sajda_recommended": false, "language": "en", "name": "Asad", "transelator_en_name": "Muhammad Asad", "format": "text", "type": "translation", "ayah_number": 3549, "text": "Say: \u201cWhether you flee from [natural] death or from being slain [in battle], flight will not profit you - for, however you fare, you are not [allowed] to enjoy life for more than a little while!\u201d"}, {"id": 221651, "identifier": "en.asad", "surah_number": 33, "surah_ar_name": "\u0633\u0648\u0631\u0629 \u0627\u0644\u0623\u062d\u0632\u0627\u0628", "surah_en_name": "Al-Ahzaab", "surah_en_name_translation": "The Clans", "revelation_type": "Medinan", "juz": 21, "manzil": 5, "page": 420, "ruku": 362, "hizb_quarter": 167, "sajda": false, "sajda_id": 0, "sajda_obligatory": false, "sajda_recommended": false, "language": "en", "name": "Asad", "transelator_en_name": "Muhammad Asad", "format": "text", "type": "translation", "ayah_number": 3550, "text": "Say: \u201cWho is there that could keep you away from God if it be His will to harm you, or if it be His will to show you mercy?\u201d For, [do they not know that] besides God they can find none to protect them, and none to bring them succour?"}, {"id": 221652, "identifier": "en.asad", "surah_number": 33, "surah_ar_name": "\u0633\u0648\u0631\u0629 \u0627\u0644\u0623\u062d\u0632\u0627\u0628", "surah_en_name": "Al-Ahzaab", "surah_en_name_translation": "The Clans", "revelation_type": "Medinan", "juz": 21, "manzil": 5, "page": 420, "ruku": 362, "hizb_quarter": 168, "sajda": false, "sajda_id": 0, "sajda_obligatory": false, "sajda_recommended": false, "language": "en", "name": "Asad", "transelator_en_name": "Muhammad Asad", "format": "text", "type": "translation", "ayah_number": 3551, "text": "God is indeed aware of those of you who would divert others [from fighting in His cause], as well as of those who say to their brethren, \u201cCome hither to us [and face the enemy]!\u201d \u2014 The while they [themselves] join battle but seldom,"}, {"id": 221653, "identifier": "en.asad", "surah_number": 33, "surah_ar_name": "\u0633\u0648\u0631\u0629 \u0627\u0644\u0623\u062d\u0632\u0627\u0628", "surah_en_name": "Al-Ahzaab", "surah_en_name_translation": "The Clans", "revelation_type": "Medinan", "juz": 21, "manzil": 5, "page": 420, "ruku": 362, "hizb_quarter": 168, "sajda": false, "sajda_id": 0, "sajda_obligatory": false, "sajda_recommended": false, "language": "en", "name": "Asad", "transelator_en_name": "Muhammad Asad", "format": "text", "type": "translation", "ayah_number": 3552, "text": "begrudging you all help. But then, when danger threatens, thou canst see them looking to thee [for help, O Prophet], their eyes rolling [in terror] like [the eyes of] one who is overshadowed by death: yet as soon as the danger has passed, they will assail you [believers] with sharp tongues, begrudging you all that is good! [People like] these have never known faith - and therefore God will cause all their works to come to nought: for this is indeed easy for God."}, {"id": 221654, "identifier": "en.asad", "surah_number": 33, "surah_ar_name": "\u0633\u0648\u0631\u0629 \u0627\u0644\u0623\u062d\u0632\u0627\u0628", "surah_en_name": "Al-Ahzaab", "surah_en_name_translation": "The Clans", "revelation_type": "Medinan", "juz": 21, "manzil": 5, "page": 420, "ruku": 362, "hizb_quarter": 168, "sajda": false, "sajda_id": 0, "sajda_obligatory": false, "sajda_recommended": false, "language": "en", "name": "Asad", "transelator_en_name": "Muhammad Asad", "format": "text", "type": "translation", "ayah_number": 3553, "text": "They think that the Confederates have not [really] withdrawn; and should the Confederates return, these [hypocrites] would prefer to be in the desert, among the bedouin, asking for news about you, [O believers, from far away;] and even were they to find themselves in your midst, they would but make a pretence at fighting [by your side]."}, {"id": 221655, "identifier": "en.asad", "surah_number": 33, "surah_ar_name": "\u0633\u0648\u0631\u0629 \u0627\u0644\u0623\u062d\u0632\u0627\u0628", "surah_en_name": "Al-Ahzaab", "surah_en_name_translation": "The Clans", "revelation_type": "Medinan", "juz": 21, "manzil": 5, "page": 420, "ruku": 363, "hizb_quarter": 168, "sajda": false, "sajda_id": 0, "sajda_obligatory": false, "sajda_recommended": false, "language": "en", "name": "Asad", "transelator_en_name": "Muhammad Asad", "format": "text", "type": "translation", "ayah_number": 3554, "text": "VERILY, in the Apostle of God you have a good example for everyone who looks forward [with hope and awe] to God and the Last Day, and remembers God unceasingly."}, {"id": 221656, "identifier": "en.asad", "surah_number": 33, "surah_ar_name": "\u0633\u0648\u0631\u0629 \u0627\u0644\u0623\u062d\u0632\u0627\u0628", "surah_en_name": "Al-Ahzaab", "surah_en_name_translation": "The Clans", "revelation_type": "Medinan", "juz": 21, "manzil": 5, "page": 420, "ruku": 363, "hizb_quarter": 168, "sajda": false, "sajda_id": 0, "sajda_obligatory": false, "sajda_recommended": false, "language": "en", "name": "Asad", "transelator_en_name": "Muhammad Asad", "format": "text", "type": "translation", "ayah_number": 3555, "text": "And [so,] when the believers saw the Con\u00adfederates [advancing against them], they said, \u201cThis is what God and His Apostle have promised us!\u201d- and, \u201cTruly spoke God and His Apostle!\u201d and all this but increased their faith and their readiness to surrender themselves unto God."}, {"id": 221657, "identifier": "en.asad", "surah_number": 33, "surah_ar_name": "\u0633\u0648\u0631\u0629 \u0627\u0644\u0623\u062d\u0632\u0627\u0628", "surah_en_name": "Al-Ahzaab", "surah_en_name_translation": "The Clans", "revelation_type": "Medinan", "juz": 21, "manzil": 5, "page": 421, "ruku": 363, "hizb_quarter": 168, "sajda": false, "sajda_id": 0, "sajda_obligatory": false, "sajda_recommended": false, "language": "en", "name": "Asad", "transelator_en_name": "Muhammad Asad", "format": "text", "type": "translation", "ayah_number": 3556, "text": "Among the believers are men who have [always] been true to what they have vowed before God; and among them are such as have [already] redeemed their pledge by death, and such as yet await [its fulfillment] without having changed [their resolve] in the least."}, {"id": 221658, "identifier": "en.asad", "surah_number": 33, "surah_ar_name": "\u0633\u0648\u0631\u0629 \u0627\u0644\u0623\u062d\u0632\u0627\u0628", "surah_en_name": "Al-Ahzaab", "surah_en_name_translation": "The Clans", "revelation_type": "Medinan", "juz": 21, "manzil": 5, "page": 421, "ruku": 363, "hizb_quarter": 168, "sajda": false, "sajda_id": 0, "sajda_obligatory": false, "sajda_recommended": false, "language": "en", "name": "Asad", "transelator_en_name": "Muhammad Asad", "format": "text", "type": "translation", "ayah_number": 3557, "text": "[Such trials are imposed upon man] so that God may reward the truthful for having been true to their word, and cause the hypocrites to suffer - if that be His will - or [if they repent,] accept their repen\u00adtance: for, verily, God is indeed much-forgiving, a dispenser of grace!"}, {"id": 221659, "identifier": "en.asad", "surah_number": 33, "surah_ar_name": "\u0633\u0648\u0631\u0629 \u0627\u0644\u0623\u062d\u0632\u0627\u0628", "surah_en_name": "Al-Ahzaab", "surah_en_name_translation": "The Clans", "revelation_type": "Medinan", "juz": 21, "manzil": 5, "page": 421, "ruku": 363, "hizb_quarter": 168, "sajda": false, "sajda_id": 0, "sajda_obligatory": false, "sajda_recommended": false, "language": "en", "name": "Asad", "transelator_en_name": "Muhammad Asad", "format": "text", "type": "translation", "ayah_number": 3558, "text": "Thus, for all their fury, God repulsed those who were bent on denying the truth; no advantage did they gain, since God was enough to [protect] the believers in battle - seeing that God is most powerful, almighty;"}, {"id": 221660, "identifier": "en.asad", "surah_number": 33, "surah_ar_name": "\u0633\u0648\u0631\u0629 \u0627\u0644\u0623\u062d\u0632\u0627\u0628", "surah_en_name": "Al-Ahzaab", "surah_en_name_translation": "The Clans", "revelation_type": "Medinan", "juz": 21, "manzil": 5, "page": 421, "ruku": 363, "hizb_quarter": 168, "sajda": false, "sajda_id": 0, "sajda_obligatory": false, "sajda_recommended": false, "language": "en", "name": "Asad", "transelator_en_name": "Muhammad Asad", "format": "text", "type": "translation", "ayah_number": 3559, "text": "and He brought down from their strongholds those of the followers of earlier reve\u00adlation who had aided the aggressors, and cast terror into their hearts: some you slew, and some you made captive;"}, {"id": 221661, "identifier": "en.asad", "surah_number": 33, "surah_ar_name": "\u0633\u0648\u0631\u0629 \u0627\u0644\u0623\u062d\u0632\u0627\u0628", "surah_en_name": "Al-Ahzaab", "surah_en_name_translation": "The Clans", "revelation_type": "Medinan", "juz": 21, "manzil": 5, "page": 421, "ruku": 363, "hizb_quarter": 168, "sajda": false, "sajda_id": 0, "sajda_obligatory": false, "sajda_recommended": false, "language": "en", "name": "Asad", "transelator_en_name": "Muhammad Asad", "format": "text", "type": "translation", "ayah_number": 3560, "text": "and He made you heirs to their lands, and their houses, and their goods - and [promised you] lands on which you had never yet set foot: for God has indeed the power to will anything."}, {"id": 221662, "identifier": "en.asad", "surah_number": 33, "surah_ar_name": "\u0633\u0648\u0631\u0629 \u0627\u0644\u0623\u062d\u0632\u0627\u0628", "surah_en_name": "Al-Ahzaab", "surah_en_name_translation": "The Clans", "revelation_type": "Medinan", "juz": 21, "manzil": 5, "page": 421, "ruku": 364, "hizb_quarter": 168, "sajda": false, "sajda_id": 0, "sajda_obligatory": false, "sajda_recommended": false, "language": "en", "name": "Asad", "transelator_en_name": "Muhammad Asad", "format": "text", "type": "translation", "ayah_number": 3561, "text": "O PROPHET! Say unto thy wives: \u201cIf you desire [but] the life of this world and its charms - well, then, I shall provide for you and release you in a becoming manner;"}, {"id": 221663, "identifier": "en.asad", "surah_number": 33, "surah_ar_name": "\u0633\u0648\u0631\u0629 \u0627\u0644\u0623\u062d\u0632\u0627\u0628", "surah_en_name": "Al-Ahzaab", "surah_en_name_translation": "The Clans", "revelation_type": "Medinan", "juz": 21, "manzil": 5, "page": 421, "ruku": 364, "hizb_quarter": 168, "sajda": false, "sajda_id": 0, "sajda_obligatory": false, "sajda_recommended": false, "language": "en", "name": "Asad", "transelator_en_name": "Muhammad Asad", "format": "text", "type": "translation", "ayah_number": 3562, "text": "but if you desire God and His Apostle, and [thus the good of] the life in the hereafter, then [know that], verily, for the doers of good among you God has readied a mighty reward!\u201d"}, {"id": 221664, "identifier": "en.asad", "surah_number": 33, "surah_ar_name": "\u0633\u0648\u0631\u0629 \u0627\u0644\u0623\u062d\u0632\u0627\u0628", "surah_en_name": "Al-Ahzaab", "surah_en_name_translation": "The Clans", "revelation_type": "Medinan", "juz": 21, "manzil": 5, "page": 421, "ruku": 364, "hizb_quarter": 168, "sajda": false, "sajda_id": 0, "sajda_obligatory": false, "sajda_recommended": false, "language": "en", "name": "Asad", "transelator_en_name": "Muhammad Asad", "format": "text", "type": "translation", "ayah_number": 3563, "text": "O wives of the Prophet! If any of you were to become guilty of manifestly immoral conduct, double [that of other sinners] would be her suffering [in the hereafter]: for that is indeed easy for God."}, {"id": 221665, "identifier": "en.asad", "surah_number": 33, "surah_ar_name": "\u0633\u0648\u0631\u0629 \u0627\u0644\u0623\u062d\u0632\u0627\u0628", "surah_en_name": "Al-Ahzaab", "surah_en_name_translation": "The Clans", "revelation_type": "Medinan", "juz": 22, "manzil": 5, "page": 422, "ruku": 364, "hizb_quarter": 169, "sajda": false, "sajda_id": 0, "sajda_obligatory": false, "sajda_recommended": false, "language": "en", "name": "Asad", "transelator_en_name": "Muhammad Asad", "format": "text", "type": "translation", "ayah_number": 3564, "text": "But if any of you devoutly obeys God and His Apostle and does good deeds, on her shall We bestow her reward twice-over: for We shall have readied for her a most excellent sustenance [in the life to come]."}, {"id": 221666, "identifier": "en.asad", "surah_number": 33, "surah_ar_name": "\u0633\u0648\u0631\u0629 \u0627\u0644\u0623\u062d\u0632\u0627\u0628", "surah_en_name": "Al-Ahzaab", "surah_en_name_translation": "The Clans", "revelation_type": "Medinan", "juz": 22, "manzil": 5, "page": 422, "ruku": 364, "hizb_quarter": 169, "sajda": false, "sajda_id": 0, "sajda_obligatory": false, "sajda_recommended": false, "language": "en", "name": "Asad", "transelator_en_name": "Muhammad Asad", "format": "text", "type": "translation", "ayah_number": 3565, "text": "O wives of the Prophet! You are not like any of the [other] women, provided that you remain [truly] conscious of God. Hence, be not over-soft in your speech, lest any whose heart is diseased should be moved to desire [you]: but, withal, speak in a kindly way."}, {"id": 221667, "identifier": "en.asad", "surah_number": 33, "surah_ar_name": "\u0633\u0648\u0631\u0629 \u0627\u0644\u0623\u062d\u0632\u0627\u0628", "surah_en_name": "Al-Ahzaab", "surah_en_name_translation": "The Clans", "revelation_type": "Medinan", "juz": 22, "manzil": 5, "page": 422, "ruku": 364, "hizb_quarter": 169, "sajda": false, "sajda_id": 0, "sajda_obligatory": false, "sajda_recommended": false, "language": "en", "name": "Asad", "transelator_en_name": "Muhammad Asad", "format": "text", "type": "translation", "ayah_number": 3566, "text": "And abide quietly in your homes, and do not flaunt your charms as they used to flaunt them in the old days of pagan ignorance; and be constant in prayer, and render the purifying dues, and pay heed unto God and His Apostle: for God only wants to remove from you all that might be loathsome, O you members of the [Prophet\u2019s] household, and to purify you to utmost purity."}, {"id": 221668, "identifier": "en.asad", "surah_number": 33, "surah_ar_name": "\u0633\u0648\u0631\u0629 \u0627\u0644\u0623\u062d\u0632\u0627\u0628", "surah_en_name": "Al-Ahzaab", "surah_en_name_translation": "The Clans", "revelation_type": "Medinan", "juz": 22, "manzil": 5, "page": 422, "ruku": 364, "hizb_quarter": 169, "sajda": false, "sajda_id": 0, "sajda_obligatory": false, "sajda_recommended": false, "language": "en", "name": "Asad", "transelator_en_name": "Muhammad Asad", "format": "text", "type": "translation", "ayah_number": 3567, "text": "And bear in mind all that is recited in your homes of God\u2019s messages and [His] wisdom: for God is unfathomable [in His wisdom], all-aware."}, {"id": 221669, "identifier": "en.asad", "surah_number": 33, "surah_ar_name": "\u0633\u0648\u0631\u0629 \u0627\u0644\u0623\u062d\u0632\u0627\u0628", "surah_en_name": "Al-Ahzaab", "surah_en_name_translation": "The Clans", "revelation_type": "Medinan", "juz": 22, "manzil": 5, "page": 422, "ruku": 365, "hizb_quarter": 169, "sajda": false, "sajda_id": 0, "sajda_obligatory": false, "sajda_recommended": false, "language": "en", "name": "Asad", "transelator_en_name": "Muhammad Asad", "format": "text", "type": "translation", "ayah_number": 3568, "text": "VERILY, for all men and women who have sur\u00adrendered themselves unto God, and all believing men and believing women, and all truly devout men and truly devout women, and all men and women who are true to their word, and all men and women who are patient in adversity, and all men and women who humble themselves [before God], and all men and women who give in charity, and all self-denying men and self-denying women, and all men and women who are mindful of their chastity, and all men and women who remember God unceasingly: for [all of] them has God readied forgiveness of sins and a mighty reward."}, {"id": 221670, "identifier": "en.asad", "surah_number": 33, "surah_ar_name": "\u0633\u0648\u0631\u0629 \u0627\u0644\u0623\u062d\u0632\u0627\u0628", "surah_en_name": "Al-Ahzaab", "surah_en_name_translation": "The Clans", "revelation_type": "Medinan", "juz": 22, "manzil": 5, "page": 423, "ruku": 365, "hizb_quarter": 169, "sajda": false, "sajda_id": 0, "sajda_obligatory": false, "sajda_recommended": false, "language": "en", "name": "Asad", "transelator_en_name": "Muhammad Asad", "format": "text", "type": "translation", "ayah_number": 3569, "text": "Now whenever God and His Apostle have decided a matter, it is not for a believing man or a believing woman to claim freedom of choice insofar as they themselves are concerned: for he who [thus] rebels against God and His Apostle has already, most obviously, gone astray."}, {"id": 221671, "identifier": "en.asad", "surah_number": 33, "surah_ar_name": "\u0633\u0648\u0631\u0629 \u0627\u0644\u0623\u062d\u0632\u0627\u0628", "surah_en_name": "Al-Ahzaab", "surah_en_name_translation": "The Clans", "revelation_type": "Medinan", "juz": 22, "manzil": 5, "page": 423, "ruku": 365, "hizb_quarter": 169, "sajda": false, "sajda_id": 0, "sajda_obligatory": false, "sajda_recommended": false, "language": "en", "name": "Asad", "transelator_en_name": "Muhammad Asad", "format": "text", "type": "translation", "ayah_number": 3570, "text": "AND LO, [O Muhammad,] thou didst say unto the one to whom God had shown favour and to whom thou hadst shown favour, \u201cHold on to thy wife, and remain conscious of God!\u201d And [thus] wouldst thou hide within thyself something that God was about to bring to light for thou didst stand in awe of [what] people [might think], whereas it was God alone of whom thou shouldst have stood in awe! [But] then, when Zayd had come to the end of his union with her, We gave her to thee in marriage, so that [in future] no blame should attach to the be\u00adlievers for [marrying] the spouses of their adopted children when the latter have come to the end of their union with them. And [thus] God\u2019s will was done."}, {"id": 221672, "identifier": "en.asad", "surah_number": 33, "surah_ar_name": "\u0633\u0648\u0631\u0629 \u0627\u0644\u0623\u062d\u0632\u0627\u0628", "surah_en_name": "Al-Ahzaab", "surah_en_name_translation": "The Clans", "revelation_type": "Medinan", "juz": 22, "manzil": 5, "page": 423, "ruku": 365, "hizb_quarter": 169, "sajda": false, "sajda_id": 0, "sajda_obligatory": false, "sajda_recommended": false, "language": "en", "name": "Asad", "transelator_en_name": "Muhammad Asad", "format": "text", "type": "translation", "ayah_number": 3571, "text": "[Hence,] no blame whatever attaches to the Prophet for [having done] what God has ordained for him. [Indeed, such was] God\u2019s way with those that have passed away aforetime and [remember that] God\u2019s will is always destiny absolute-;"}, {"id": 221673, "identifier": "en.asad", "surah_number": 33, "surah_ar_name": "\u0633\u0648\u0631\u0629 \u0627\u0644\u0623\u062d\u0632\u0627\u0628", "surah_en_name": "Al-Ahzaab", "surah_en_name_translation": "The Clans", "revelation_type": "Medinan", "juz": 22, "manzil": 5, "page": 423, "ruku": 365, "hizb_quarter": 169, "sajda": false, "sajda_id": 0, "sajda_obligatory": false, "sajda_recommended": false, "language": "en", "name": "Asad", "transelator_en_name": "Muhammad Asad", "format": "text", "type": "translation", "ayah_number": 3572, "text": "[and such will always be His way with] those who convey God\u2019s messages [to the world], and stand in awe of Him, and hold none but God in awe: for none can take count [of man\u2019s doings] as God does!"}, {"id": 221637, "identifier": "en.asad", "surah_number": 33, "surah_ar_name": "\u0633\u0648\u0631\u0629 \u0627\u0644\u0623\u062d\u0632\u0627\u0628", "surah_en_name": "Al-Ahzaab", "surah_en_name_translation": "The Clans", "revelation_type": "Medinan", "juz": 22, "manzil": 5, "page": 423, "ruku": 365, "hizb_quarter": 169, "sajda": false, "sajda_id": 0, "sajda_obligatory": false, "sajda_recommended": false, "language": "en", "name": "Asad", "transelator_en_name": "Muhammad Asad", "format": "text", "type": "translation", "ayah_number": 3573, "text": "[And know, O believers, that] Muhammad is not the father of any one of your men, but is God\u2019s Apostle and the Seal of all Prophets. And God has indeed full knowledge of everything."}, {"id": 221385, "identifier": "en.asad", "surah_number": 33, "surah_ar_name": "\u0633\u0648\u0631\u0629 \u0627\u0644\u0623\u062d\u0632\u0627\u0628", "surah_en_name": "Al-Ahzaab", "surah_en_name_translation": "The Clans", "revelation_type": "Medinan", "juz": 22, "manzil": 5, "page": 423, "ruku": 366, "hizb_quarter": 169, "sajda": false, "sajda_id": 0, "sajda_obligatory": false, "sajda_recommended": false, "language": "en", "name": "Asad", "transelator_en_name": "Muhammad Asad", "format": "text", "type": "translation", "ayah_number": 3574, "text": "O YOU who have attained to faith! Remember God with unceasing remembrance,"}, {"id": 221425, "identifier": "en.asad", "surah_number": 33, "surah_ar_name": "\u0633\u0648\u0631\u0629 \u0627\u0644\u0623\u062d\u0632\u0627\u0628", "surah_en_name": "Al-Ahzaab", "surah_en_name_translation": "The Clans", "revelation_type": "Medinan", "juz": 22, "manzil": 5, "page": 423, "ruku": 366, "hizb_quarter": 169, "sajda": false, "sajda_id": 0, "sajda_obligatory": false, "sajda_recommended": false, "language": "en", "name": "Asad", "transelator_en_name": "Muhammad Asad", "format": "text", "type": "translation", "ayah_number": 3575, "text": "and extol His limitless glory from morn to evening."}, {"id": 221674, "identifier": "en.asad", "surah_number": 33, "surah_ar_name": "\u0633\u0648\u0631\u0629 \u0627\u0644\u0623\u062d\u0632\u0627\u0628", "surah_en_name": "Al-Ahzaab", "surah_en_name_translation": "The Clans", "revelation_type": "Medinan", "juz": 22, "manzil": 5, "page": 423, "ruku": 366, "hizb_quarter": 169, "sajda": false, "sajda_id": 0, "sajda_obligatory": false, "sajda_recommended": false, "language": "en", "name": "Asad", "transelator_en_name": "Muhammad Asad", "format": "text", "type": "translation", "ayah_number": 3576, "text": "He it is who bestows His blessings upon you, with His angels [echoing Him], so that He might take you out of the depths of darkness into the light. And, indeed, a dispenser of grace is He unto the believers."}, {"id": 221675, "identifier": "en.asad", "surah_number": 33, "surah_ar_name": "\u0633\u0648\u0631\u0629 \u0627\u0644\u0623\u062d\u0632\u0627\u0628", "surah_en_name": "Al-Ahzaab", "surah_en_name_translation": "The Clans", "revelation_type": "Medinan", "juz": 22, "manzil": 5, "page": 424, "ruku": 366, "hizb_quarter": 169, "sajda": false, "sajda_id": 0, "sajda_obligatory": false, "sajda_recommended": false, "language": "en", "name": "Asad", "transelator_en_name": "Muhammad Asad", "format": "text", "type": "translation", "ayah_number": 3577, "text": "On the Day when they meet Him, they will be welcomed with the greeting, \u201cPeace\u201d; and He will have readied for them a most excellent reward."}, {"id": 221676, "identifier": "en.asad", "surah_number": 33, "surah_ar_name": "\u0633\u0648\u0631\u0629 \u0627\u0644\u0623\u062d\u0632\u0627\u0628", "surah_en_name": "Al-Ahzaab", "surah_en_name_translation": "The Clans", "revelation_type": "Medinan", "juz": 22, "manzil": 5, "page": 424, "ruku": 366, "hizb_quarter": 169, "sajda": false, "sajda_id": 0, "sajda_obligatory": false, "sajda_recommended": false, "language": "en", "name": "Asad", "transelator_en_name": "Muhammad Asad", "format": "text", "type": "translation", "ayah_number": 3578, "text": "[And as for thee,] O Prophet - behold, We have sent thee as a witness [to the truth], and as a herald of glad tidings and a warner,"}, {"id": 221677, "identifier": "en.asad", "surah_number": 33, "surah_ar_name": "\u0633\u0648\u0631\u0629 \u0627\u0644\u0623\u062d\u0632\u0627\u0628", "surah_en_name": "Al-Ahzaab", "surah_en_name_translation": "The Clans", "revelation_type": "Medinan", "juz": 22, "manzil": 5, "page": 424, "ruku": 366, "hizb_quarter": 169, "sajda": false, "sajda_id": 0, "sajda_obligatory": false, "sajda_recommended": false, "language": "en", "name": "Asad", "transelator_en_name": "Muhammad Asad", "format": "text", "type": "translation", "ayah_number": 3579, "text": "and as one who summons [all men] to God by His leave, and as a light-giving beacon."}, {"id": 221678, "identifier": "en.asad", "surah_number": 33, "surah_ar_name": "\u0633\u0648\u0631\u0629 \u0627\u0644\u0623\u062d\u0632\u0627\u0628", "surah_en_name": "Al-Ahzaab", "surah_en_name_translation": "The Clans", "revelation_type": "Medinan", "juz": 22, "manzil": 5, "page": 424, "ruku": 366, "hizb_quarter": 169, "sajda": false, "sajda_id": 0, "sajda_obligatory": false, "sajda_recommended": false, "language": "en", "name": "Asad", "transelator_en_name": "Muhammad Asad", "format": "text", "type": "translation", "ayah_number": 3580, "text": "And [so,] convey to the believers the glad tiding that a great bounty from God awaits them;"}, {"id": 221679, "identifier": "en.asad", "surah_number": 33, "surah_ar_name": "\u0633\u0648\u0631\u0629 \u0627\u0644\u0623\u062d\u0632\u0627\u0628", "surah_en_name": "Al-Ahzaab", "surah_en_name_translation": "The Clans", "revelation_type": "Medinan", "juz": 22, "manzil": 5, "page": 424, "ruku": 366, "hizb_quarter": 169, "sajda": false, "sajda_id": 0, "sajda_obligatory": false, "sajda_recommended": false, "language": "en", "name": "Asad", "transelator_en_name": "Muhammad Asad", "format": "text", "type": "translation", "ayah_number": 3581, "text": "and defer not to [the likes and dislikes of] the deniers of the truth and the hypocrites, and disregard their hurtful talk, and place thy trust in God: for none is as worthy of trust as God."}, {"id": 221681, "identifier": "en.asad", "surah_number": 33, "surah_ar_name": "\u0633\u0648\u0631\u0629 \u0627\u0644\u0623\u062d\u0632\u0627\u0628", "surah_en_name": "Al-Ahzaab", "surah_en_name_translation": "The Clans", "revelation_type": "Medinan", "juz": 22, "manzil": 5, "page": 424, "ruku": 366, "hizb_quarter": 169, "sajda": false, "sajda_id": 0, "sajda_obligatory": false, "sajda_recommended": false, "language": "en", "name": "Asad", "transelator_en_name": "Muhammad Asad", "format": "text", "type": "translation", "ayah_number": 3582, "text": "O YOU who have attained to faith! If you marry believing women and then divorce them ere you have touched them, you have no reason to expect, and to calculate, any waiting period on their part: hence, make [at once] provision for them, and release them in a becoming manner."}, {"id": 221682, "identifier": "en.asad", "surah_number": 33, "surah_ar_name": "\u0633\u0648\u0631\u0629 \u0627\u0644\u0623\u062d\u0632\u0627\u0628", "surah_en_name": "Al-Ahzaab", "surah_en_name_translation": "The Clans", "revelation_type": "Medinan", "juz": 22, "manzil": 5, "page": 424, "ruku": 366, "hizb_quarter": 169, "sajda": false, "sajda_id": 0, "sajda_obligatory": false, "sajda_recommended": false, "language": "en", "name": "Asad", "transelator_en_name": "Muhammad Asad", "format": "text", "type": "translation", "ayah_number": 3583, "text": "O PROPHET! Behold, We have made lawful to thee thy wives unto whom thou hast paid their dowers, as well as those whom thy right hand has come to possess from among the captives of war whom God has bestowed upon thee. And [We have made lawful to thee] the daughters of thy paternal uncles and aunts, and the daughters of thy maternal uncles and aunts, who have migrated with thee [to Yathrib]; and any believing woman who offers herself freely to the Prophet and whom the Prophet might be willing to wed: [this latter being but] a privilege for thee, and not for other believers - [seeing that] We have already made known what We have enjoined upon them with regard to their wives and those whom their right hands may possess. [And] in order that thou be not burdened with [undue] anxiety - for God is indeed much-forgiving, a dispenser of grace \u2013"}, {"id": 221683, "identifier": "en.asad", "surah_number": 33, "surah_ar_name": "\u0633\u0648\u0631\u0629 \u0627\u0644\u0623\u062d\u0632\u0627\u0628", "surah_en_name": "Al-Ahzaab", "surah_en_name_translation": "The Clans", "revelation_type": "Medinan", "juz": 22, "manzil": 5, "page": 425, "ruku": 366, "hizb_quarter": 170, "sajda": false, "sajda_id": 0, "sajda_obligatory": false, "sajda_recommended": false, "language": "en", "name": "Asad", "transelator_en_name": "Muhammad Asad", "format": "text", "type": "translation", "ayah_number": 3584, "text": "[know that] thou mayest put off for a time whichever of them thou pleasest, and mayest take unto thee whichever thou pleasest; and [that,] if thou seek out any from whom thou hast kept away [for a time], thou wilt incur no sin [thereby]: this will make it more likely that their eyes are gladdened [whenever they see thee], and that they do not grieve [whenever they are overlooked], and that all of them may find contentment in whatever thou hast to give them: for God [alone] knows what is in your hearts - and God is indeed all-knowing, for\u00adbearing."}, {"id": 221684, "identifier": "en.asad", "surah_number": 33, "surah_ar_name": "\u0633\u0648\u0631\u0629 \u0627\u0644\u0623\u062d\u0632\u0627\u0628", "surah_en_name": "Al-Ahzaab", "surah_en_name_translation": "The Clans", "revelation_type": "Medinan", "juz": 22, "manzil": 5, "page": 425, "ruku": 366, "hizb_quarter": 170, "sajda": false, "sajda_id": 0, "sajda_obligatory": false, "sajda_recommended": false, "language": "en", "name": "Asad", "transelator_en_name": "Muhammad Asad", "format": "text", "type": "translation", "ayah_number": 3585, "text": "No [other] women shall henceforth be lawful to thee nor art thou [allowed] to supplant [any of] them by other wives, even though their beauty should please thee greatly -: [none shall be lawful to thee] beyond those whom thou [already] hast come to possess. And God keeps watch over everything."}, {"id": 221685, "identifier": "en.asad", "surah_number": 33, "surah_ar_name": "\u0633\u0648\u0631\u0629 \u0627\u0644\u0623\u062d\u0632\u0627\u0628", "surah_en_name": "Al-Ahzaab", "surah_en_name_translation": "The Clans", "revelation_type": "Medinan", "juz": 22, "manzil": 5, "page": 425, "ruku": 367, "hizb_quarter": 170, "sajda": false, "sajda_id": 0, "sajda_obligatory": false, "sajda_recommended": false, "language": "en", "name": "Asad", "transelator_en_name": "Muhammad Asad", "format": "text", "type": "translation", "ayah_number": 3586, "text": "O YOU who have attained to faith! Do not enter the Prophet\u2019s dwellings unless you are given leave; [and when invited] to a meal, do not come [so early as] to wait for it to be readied: but whenever you are invited, enter [at the proper time]; and when you have partaken of the meal, disperse without lingering for the sake of mere talk: that, behold, might give offence to the Prophet, and yet he might feel shy of [asking] you [to leave]: but God is not shy of [teaching you] what is right. And [as for the Prophet\u2019s wives,] whenever you ask them for anything that you need, ask them from behind a screen: this will but deepen the purity of your hearts and theirs. Moreover, it does not behove you to give offence to God\u2019s Apostle - just as it would not behove you ever to marry his widows after he has passed away: that, verily, would be an enormity in the sight of God."}, {"id": 221686, "identifier": "en.asad", "surah_number": 33, "surah_ar_name": "\u0633\u0648\u0631\u0629 \u0627\u0644\u0623\u062d\u0632\u0627\u0628", "surah_en_name": "Al-Ahzaab", "surah_en_name_translation": "The Clans", "revelation_type": "Medinan", "juz": 22, "manzil": 5, "page": 425, "ruku": 367, "hizb_quarter": 170, "sajda": false, "sajda_id": 0, "sajda_obligatory": false, "sajda_recommended": false, "language": "en", "name": "Asad", "transelator_en_name": "Muhammad Asad", "format": "text", "type": "translation", "ayah_number": 3587, "text": "Whether you do anything openly or in secret, [remember that,] verily, God has full knowledge of everything."}, {"id": 221687, "identifier": "en.asad", "surah_number": 33, "surah_ar_name": "\u0633\u0648\u0631\u0629 \u0627\u0644\u0623\u062d\u0632\u0627\u0628", "surah_en_name": "Al-Ahzaab", "surah_en_name_translation": "The Clans", "revelation_type": "Medinan", "juz": 22, "manzil": 5, "page": 426, "ruku": 367, "hizb_quarter": 170, "sajda": false, "sajda_id": 0, "sajda_obligatory": false, "sajda_recommended": false, "language": "en", "name": "Asad", "transelator_en_name": "Muhammad Asad", "format": "text", "type": "translation", "ayah_number": 3588, "text": "[However,] it is no sin for them [to appear freely] before their fathers, or their sons, or their brothers, or their brothers\u2019 sons, or their sisters\u2019 sons, or their womenfolk, or such [male slaves] as their right hands may possess. But [always, O wives of the Prophet,] remain con\u00adscious of God - for, behold, God is witness unto everything."}, {"id": 221688, "identifier": "en.asad", "surah_number": 33, "surah_ar_name": "\u0633\u0648\u0631\u0629 \u0627\u0644\u0623\u062d\u0632\u0627\u0628", "surah_en_name": "Al-Ahzaab", "surah_en_name_translation": "The Clans", "revelation_type": "Medinan", "juz": 22, "manzil": 5, "page": 426, "ruku": 367, "hizb_quarter": 170, "sajda": false, "sajda_id": 0, "sajda_obligatory": false, "sajda_recommended": false, "language": "en", "name": "Asad", "transelator_en_name": "Muhammad Asad", "format": "text", "type": "translation", "ayah_number": 3589, "text": "Verily, God and His angels bless the Prophet: [hence,] O you who have attained to faith, bless him and give yourselves up [to his guidance] in utter self-surrender!"}, {"id": 221689, "identifier": "en.asad", "surah_number": 33, "surah_ar_name": "\u0633\u0648\u0631\u0629 \u0627\u0644\u0623\u062d\u0632\u0627\u0628", "surah_en_name": "Al-Ahzaab", "surah_en_name_translation": "The Clans", "revelation_type": "Medinan", "juz": 22, "manzil": 5, "page": 426, "ruku": 367, "hizb_quarter": 170, "sajda": false, "sajda_id": 0, "sajda_obligatory": false, "sajda_recommended": false, "language": "en", "name": "Asad", "transelator_en_name": "Muhammad Asad", "format": "text", "type": "translation", "ayah_number": 3590, "text": "Verily, as for those who [knowingly] affront God and His Apostle - God will reject them in this world and in the life to come; and shameful suffering will He ready for them."}, {"id": 221690, "identifier": "en.asad", "surah_number": 33, "surah_ar_name": "\u0633\u0648\u0631\u0629 \u0627\u0644\u0623\u062d\u0632\u0627\u0628", "surah_en_name": "Al-Ahzaab", "surah_en_name_translation": "The Clans", "revelation_type": "Medinan", "juz": 22, "manzil": 5, "page": 426, "ruku": 367, "hizb_quarter": 170, "sajda": false, "sajda_id": 0, "sajda_obligatory": false, "sajda_recommended": false, "language": "en", "name": "Asad", "transelator_en_name": "Muhammad Asad", "format": "text", "type": "translation", "ayah_number": 3591, "text": "And as for those who malign believing men and believing women without their having done any wrong - they surely burden themselves with the guilt of calumny, and [thus] with a flagrant sin!"}, {"id": 221692, "identifier": "en.asad", "surah_number": 33, "surah_ar_name": "\u0633\u0648\u0631\u0629 \u0627\u0644\u0623\u062d\u0632\u0627\u0628", "surah_en_name": "Al-Ahzaab", "surah_en_name_translation": "The Clans", "revelation_type": "Medinan", "juz": 22, "manzil": 5, "page": 426, "ruku": 368, "hizb_quarter": 170, "sajda": false, "sajda_id": 0, "sajda_obligatory": false, "sajda_recommended": false, "language": "en", "name": "Asad", "transelator_en_name": "Muhammad Asad", "format": "text", "type": "translation", "ayah_number": 3592, "text": "O Prophet! Tell thy wives and thy daughters, as well as all [other] believing women, that they should draw over themselves some of their outer garments [when in public]: this will be more con\u00adducive to their being recognized [as decent women] and not annoyed. But [withal,] God is indeed much- forgiving, a dispenser of grace!"}, {"id": 221693, "identifier": "en.asad", "surah_number": 33, "surah_ar_name": "\u0633\u0648\u0631\u0629 \u0627\u0644\u0623\u062d\u0632\u0627\u0628", "surah_en_name": "Al-Ahzaab", "surah_en_name_translation": "The Clans", "revelation_type": "Medinan", "juz": 22, "manzil": 5, "page": 426, "ruku": 368, "hizb_quarter": 171, "sajda": false, "sajda_id": 0, "sajda_obligatory": false, "sajda_recommended": false, "language": "en", "name": "Asad", "transelator_en_name": "Muhammad Asad", "format": "text", "type": "translation", "ayah_number": 3593, "text": "THUS IT IS: if the hypocrites, and they in whose hearts is disease, and they who, by spreading false rumours, would cause disturbances in the City [of the Prophet] desist not [from their hostile doings]. We shall indeed give thee mastery over them, [O Muhammad] - and then they will not remain thy neighbours in this [city] for more than a little while:"}, {"id": 221694, "identifier": "en.asad", "surah_number": 33, "surah_ar_name": "\u0633\u0648\u0631\u0629 \u0627\u0644\u0623\u062d\u0632\u0627\u0628", "surah_en_name": "Al-Ahzaab", "surah_en_name_translation": "The Clans", "revelation_type": "Medinan", "juz": 22, "manzil": 5, "page": 426, "ruku": 368, "hizb_quarter": 171, "sajda": false, "sajda_id": 0, "sajda_obligatory": false, "sajda_recommended": false, "language": "en", "name": "Asad", "transelator_en_name": "Muhammad Asad", "format": "text", "type": "translation", "ayah_number": 3594, "text": "bereft of God\u2019s grace, they shall be seized wherever they may be found, and slain one and all."}, {"id": 221695, "identifier": "en.asad", "surah_number": 33, "surah_ar_name": "\u0633\u0648\u0631\u0629 \u0627\u0644\u0623\u062d\u0632\u0627\u0628", "surah_en_name": "Al-Ahzaab", "surah_en_name_translation": "The Clans", "revelation_type": "Medinan", "juz": 22, "manzil": 5, "page": 426, "ruku": 368, "hizb_quarter": 171, "sajda": false, "sajda_id": 0, "sajda_obligatory": false, "sajda_recommended": false, "language": "en", "name": "Asad", "transelator_en_name": "Muhammad Asad", "format": "text", "type": "translation", "ayah_number": 3595, "text": "Such has been God\u2019s way with those who [sinned in like manner and] passed away aforetime - and never wilt thou find any change in God\u2019s way!"}, {"id": 221696, "identifier": "en.asad", "surah_number": 33, "surah_ar_name": "\u0633\u0648\u0631\u0629 \u0627\u0644\u0623\u062d\u0632\u0627\u0628", "surah_en_name": "Al-Ahzaab", "surah_en_name_translation": "The Clans", "revelation_type": "Medinan", "juz": 22, "manzil": 5, "page": 427, "ruku": 368, "hizb_quarter": 171, "sajda": false, "sajda_id": 0, "sajda_obligatory": false, "sajda_recommended": false, "language": "en", "name": "Asad", "transelator_en_name": "Muhammad Asad", "format": "text", "type": "translation", "ayah_number": 3596, "text": "PEOPLE will ask thee about the Last Hour. Say: \u201cKnowledge thereof rests with God alone; yet for all thou knowest, the Last Hour may well be near!\u201d"}, {"id": 221697, "identifier": "en.asad", "surah_number": 33, "surah_ar_name": "\u0633\u0648\u0631\u0629 \u0627\u0644\u0623\u062d\u0632\u0627\u0628", "surah_en_name": "Al-Ahzaab", "surah_en_name_translation": "The Clans", "revelation_type": "Medinan", "juz": 22, "manzil": 5, "page": 427, "ruku": 368, "hizb_quarter": 171, "sajda": false, "sajda_id": 0, "sajda_obligatory": false, "sajda_recommended": false, "language": "en", "name": "Asad", "transelator_en_name": "Muhammad Asad", "format": "text", "type": "translation", "ayah_number": 3597, "text": "Verily, God has rejected the deniers of the truth, and has readied for them a blazing fire,"}, {"id": 221698, "identifier": "en.asad", "surah_number": 33, "surah_ar_name": "\u0633\u0648\u0631\u0629 \u0627\u0644\u0623\u062d\u0632\u0627\u0628", "surah_en_name": "Al-Ahzaab", "surah_en_name_translation": "The Clans", "revelation_type": "Medinan", "juz": 22, "manzil": 5, "page": 427, "ruku": 368, "hizb_quarter": 171, "sajda": false, "sajda_id": 0, "sajda_obligatory": false, "sajda_recommended": false, "language": "en", "name": "Asad", "transelator_en_name": "Muhammad Asad", "format": "text", "type": "translation", "ayah_number": 3598, "text": "therein to abide beyond the count of time: no protec\u00adtor will they find, and none to bring them succour."}, {"id": 221489, "identifier": "en.asad", "surah_number": 33, "surah_ar_name": "\u0633\u0648\u0631\u0629 \u0627\u0644\u0623\u062d\u0632\u0627\u0628", "surah_en_name": "Al-Ahzaab", "surah_en_name_translation": "The Clans", "revelation_type": "Medinan", "juz": 22, "manzil": 5, "page": 427, "ruku": 368, "hizb_quarter": 171, "sajda": false, "sajda_id": 0, "sajda_obligatory": false, "sajda_recommended": false, "language": "en", "name": "Asad", "transelator_en_name": "Muhammad Asad", "format": "text", "type": "translation", "ayah_number": 3599, "text": "On the Day when their faces shall be tossed about in the fire, they will exclaim, \u201cOh, would that we had paid heed unto God, and paid heed unto the Apostle!\u201d"}, {"id": 221680, "identifier": "en.asad", "surah_number": 33, "surah_ar_name": "\u0633\u0648\u0631\u0629 \u0627\u0644\u0623\u062d\u0632\u0627\u0628", "surah_en_name": "Al-Ahzaab", "surah_en_name_translation": "The Clans", "revelation_type": "Medinan", "juz": 22, "manzil": 5, "page": 427, "ruku": 368, "hizb_quarter": 171, "sajda": false, "sajda_id": 0, "sajda_obligatory": false, "sajda_recommended": false, "language": "en", "name": "Asad", "transelator_en_name": "Muhammad Asad", "format": "text", "type": "translation", "ayah_number": 3600, "text": "And they will say: \u201cO our Sustainer! Behold, we paid heed unto our leaders and our great men, and it is they who have led us astray from the right path!"}, {"id": 221449, "identifier": "en.asad", "surah_number": 33, "surah_ar_name": "\u0633\u0648\u0631\u0629 \u0627\u0644\u0623\u062d\u0632\u0627\u0628", "surah_en_name": "Al-Ahzaab", "surah_en_name_translation": "The Clans", "revelation_type": "Medinan", "juz": 22, "manzil": 5, "page": 427, "ruku": 368, "hizb_quarter": 171, "sajda": false, "sajda_id": 0, "sajda_obligatory": false, "sajda_recommended": false, "language": "en", "name": "Asad", "transelator_en_name": "Muhammad Asad", "format": "text", "type": "translation", "ayah_number": 3601, "text": "O our Sustainer! Give them double suffering, and banish them utterly from Thy grace!\u201d"}, {"id": 221699, "identifier": "en.asad", "surah_number": 33, "surah_ar_name": "\u0633\u0648\u0631\u0629 \u0627\u0644\u0623\u062d\u0632\u0627\u0628", "surah_en_name": "Al-Ahzaab", "surah_en_name_translation": "The Clans", "revelation_type": "Medinan", "juz": 22, "manzil": 5, "page": 427, "ruku": 369, "hizb_quarter": 171, "sajda": false, "sajda_id": 0, "sajda_obligatory": false, "sajda_recommended": false, "language": "en", "name": "Asad", "transelator_en_name": "Muhammad Asad", "format": "text", "type": "translation", "ayah_number": 3602, "text": "O YOU who have attained to faith! Be not like those [children of Israel] who gave offence to Moses, and [remember that] God showed him to be innocent of whatever they alleged [against him or demanded of him]: for of great honour was he in the sight of God."}, {"id": 221700, "identifier": "en.asad", "surah_number": 33, "surah_ar_name": "\u0633\u0648\u0631\u0629 \u0627\u0644\u0623\u062d\u0632\u0627\u0628", "surah_en_name": "Al-Ahzaab", "surah_en_name_translation": "The Clans", "revelation_type": "Medinan", "juz": 22, "manzil": 5, "page": 427, "ruku": 369, "hizb_quarter": 171, "sajda": false, "sajda_id": 0, "sajda_obligatory": false, "sajda_recommended": false, "language": "en", "name": "Asad", "transelator_en_name": "Muhammad Asad", "format": "text", "type": "translation", "ayah_number": 3603, "text": "O you who have attained to faith! Remain conscious of God, and [always] speak with a will to bring out [only] what is just and true -"}, {"id": 221701, "identifier": "en.asad", "surah_number": 33, "surah_ar_name": "\u0633\u0648\u0631\u0629 \u0627\u0644\u0623\u062d\u0632\u0627\u0628", "surah_en_name": "Al-Ahzaab", "surah_en_name_translation": "The Clans", "revelation_type": "Medinan", "juz": 22, "manzil": 5, "page": 427, "ruku": 369, "hizb_quarter": 171, "sajda": false, "sajda_id": 0, "sajda_obligatory": false, "sajda_recommended": false, "language": "en", "name": "Asad", "transelator_en_name": "Muhammad Asad", "format": "text", "type": "translation", "ayah_number": 3604, "text": "[whereupon] He will cause your deeds to be virtuous, and will forgive you your sins. And [know that] whoever pays heed unto God and His Apostle has already attained to a mighty triumph."}, {"id": 221702, "identifier": "en.asad", "surah_number": 33, "surah_ar_name": "\u0633\u0648\u0631\u0629 \u0627\u0644\u0623\u062d\u0632\u0627\u0628", "surah_en_name": "Al-Ahzaab", "surah_en_name_translation": "The Clans", "revelation_type": "Medinan", "juz": 22, "manzil": 5, "page": 427, "ruku": 369, "hizb_quarter": 171, "sajda": false, "sajda_id": 0, "sajda_obligatory": false, "sajda_recommended": false, "language": "en", "name": "Asad", "transelator_en_name": "Muhammad Asad", "format": "text", "type": "translation", "ayah_number": 3605, "text": "Verily, We did offer the trust [of reason and volition] to the heavens, and the earth, and the mountains: but they refused to bear it because they were afraid of it. Yet man took it up - for, verily, he has always been prone to be most wicked, most foolish."}, {"id": 221703, "identifier": "en.asad", "surah_number": 33, "surah_ar_name": "\u0633\u0648\u0631\u0629 \u0627\u0644\u0623\u062d\u0632\u0627\u0628", "surah_en_name": "Al-Ahzaab", "surah_en_name_translation": "The Clans", "revelation_type": "Medinan", "juz": 22, "manzil": 5, "page": 427, "ruku": 369, "hizb_quarter": 171, "sajda": false, "sajda_id": 0, "sajda_obligatory": false, "sajda_recommended": false, "language": "en", "name": "Asad", "transelator_en_name": "Muhammad Asad", "format": "text", "type": "translation", "ayah_number": 3606, "text": "[And so it is] that God imposes suffering on the hypocrites, both men and women, as well as on the men and women who ascribe divinity to aught beside Him. And [so, too, it is] that God turns in His mercy unto the believing men and believing women: for God is indeed much-forgiving, a dispenser of grace!"}]